safewise-1.1.0.data/scripts/safewisectl
safewise-1.1.0.dist-info/DESCRIPTION.rst
safewise-1.1.0.dist-info/METADATA
safewise-1.1.0.dist-info/RECORD
safewise-1.1.0.dist-info/WHEEL
safewise-1.1.0.dist-info/metadata.json
safewise-1.1.0.dist-info/top_level.txt
safewiselib/__init__.py
safewiselib/_ed25519.py
safewiselib/btc.py
safewiselib/cardano.py
safewiselib/ckd_public.py
safewiselib/client.py
safewiselib/coins.json
safewiselib/coins.py
safewiselib/cosi.py
safewiselib/debuglink.py
safewiselib/device.py
safewiselib/ethereum.py
safewiselib/exceptions.py
safewiselib/firmware.py
safewiselib/lisk.py
safewiselib/log.py
safewiselib/mapping.py
safewiselib/misc.py
safewiselib/monero.py
safewiselib/nem.py
safewiselib/ontology.py
safewiselib/protobuf.py
safewiselib/ripple.py
safewiselib/stellar.py
safewiselib/tezos.py
safewiselib/tools.py
safewiselib/tx_api.py
safewiselib/ui.py
safewiselib/messages/.keep
safewiselib/messages/Address.py
safewiselib/messages/ApplyFlags.py
safewiselib/messages/ApplySettings.py
safewiselib/messages/BackupDevice.py
safewiselib/messages/ButtonAck.py
safewiselib/messages/ButtonRequest.py
safewiselib/messages/ButtonRequestType.py
safewiselib/messages/Cancel.py
safewiselib/messages/CardanoAddress.py
safewiselib/messages/CardanoGetAddress.py
safewiselib/messages/CardanoGetPublicKey.py
safewiselib/messages/CardanoPublicKey.py
safewiselib/messages/CardanoSignTx.py
safewiselib/messages/CardanoSignedTx.py
safewiselib/messages/CardanoTxAck.py
safewiselib/messages/CardanoTxInputType.py
safewiselib/messages/CardanoTxOutputType.py
safewiselib/messages/CardanoTxRequest.py
safewiselib/messages/ChangePin.py
safewiselib/messages/CipherKeyValue.py
safewiselib/messages/CipheredKeyValue.py
safewiselib/messages/ClearSession.py
safewiselib/messages/CosiCommit.py
safewiselib/messages/CosiCommitment.py
safewiselib/messages/CosiSign.py
safewiselib/messages/CosiSignature.py
safewiselib/messages/DebugLinkDecision.py
safewiselib/messages/DebugLinkFlashErase.py
safewiselib/messages/DebugLinkGetState.py
safewiselib/messages/DebugLinkLog.py
safewiselib/messages/DebugLinkMemory.py
safewiselib/messages/DebugLinkMemoryRead.py
