Metadata-Version: 2.0
Name: safewise
Version: 1.1.0
Summary: Python library for communicating with SafeWISE Hardware Wallet
Home-page: https://github.com/coinwise-io/safewise-python
Author: CoinWISE
Author-email: safewise@coinwise.io
License: LGPLv3
Platform: UNKNOWN
Classifier: License :: OSI Approved :: GNU Lesser General Public License v3 (LGPLv3)
Classifier: Operating System :: POSIX :: Linux
Classifier: Operating System :: Microsoft :: Windows
Classifier: Operating System :: MacOS :: MacOS X
Classifier: Programming Language :: Python :: 3 :: Only
Requires-Python: >=3.5
Provides-Extra: ethereum
Provides-Extra: hidapi
Requires-Dist: click (<8,>=7)
Requires-Dist: construct (>=2.9)
Requires-Dist: ecdsa (>=0.9)
Requires-Dist: libusb1 (>=1.6.4)
Requires-Dist: mnemonic (>=0.17)
Requires-Dist: pyblake2 (>=0.9.3)
Requires-Dist: requests (>=2.4.0)
Requires-Dist: setuptools (>=19.0)
Requires-Dist: typing-extensions (>=3.6)
Provides-Extra: ethereum
Requires-Dist: ethjsonrpc (>=0.3.0); extra == 'ethereum'
Requires-Dist: rlp (>=0.4.4); extra == 'ethereum'
Provides-Extra: hidapi
Requires-Dist: hidapi (>=0.7.99.post20); extra == 'hidapi'
